audio_classification_models/__init__.py
audio_classification_models/version.py
audio_classification_models/activations/__init__.py
audio_classification_models/activations/glu.py
audio_classification_models/layers/__init__.py
audio_classification_models/layers/embedding.py
audio_classification_models/layers/multihead_attention.py
audio_classification_models/layers/positional_encoding.py
audio_classification_models/layers/subsampling.py
audio_classification_models/models/__init__.py
audio_classification_models/models/conformer.py
audio_classification_models/models/contextnet.py
audio_classification_models/utils/__init__.py
audio_classification_models/utils/math_util.py
audio_classification_models/utils/shape_util.py
audio_classification_models/utils/weights.py
audio_classification_models-1.0.9.dist-info/LICENSE.md
audio_classification_models-1.0.9.dist-info/METADATA
audio_classification_models-1.0.9.dist-info/WHEEL
audio_classification_models-1.0.9.dist-info/top_level.txt
audio_classification_models-1.0.9.dist-info/RECORD
